iarahealth_stt_ctcdecoder/__init__.py
iarahealth_stt_ctcdecoder/_swigwrapper.cpython-310-darwin.so
iarahealth_stt_ctcdecoder/swigwrapper.py
iarahealth_stt_ctcdecoder-1.5.2.dist-info/COPYING
iarahealth_stt_ctcdecoder-1.5.2.dist-info/LICENSE.paddlepaddle
iarahealth_stt_ctcdecoder-1.5.2.dist-info/LICENSE.parlance
iarahealth_stt_ctcdecoder-1.5.2.dist-info/METADATA
iarahealth_stt_ctcdecoder-1.5.2.dist-info/WHEEL
iarahealth_stt_ctcdecoder-1.5.2.dist-info/top_level.txt
iarahealth_stt_ctcdecoder-1.5.2.dist-info/RECORD
