Metadata-Version: 2.1
Name: iarahealth-stt-ctcdecoder
Version: 1.5.2
Summary: Coqui STT Python decoder package.
Home-page: UNKNOWN
License: UNKNOWN
Platform: UNKNOWN
License-File: LICENSE.paddlepaddle
License-File: LICENSE.parlance
License-File: COPYING
Requires-Dist: numpy >=1.21.4
